bitmex/__init__.py
bitmex/ccxt/__init__.py
bitmex/ccxt/bitmex.py
bitmex/ccxt/abstract/bitmex.py
bitmex/ccxt/async_support/__init__.py
bitmex/ccxt/async_support/bitmex.py
bitmex/ccxt/async_support/base/__init__.py
bitmex/ccxt/async_support/base/exchange.py
bitmex/ccxt/async_support/base/throttler.py
bitmex/ccxt/async_support/base/ws/__init__.py
bitmex/ccxt/async_support/base/ws/cache.py
bitmex/ccxt/async_support/base/ws/client.py
bitmex/ccxt/async_support/base/ws/functions.py
bitmex/ccxt/async_support/base/ws/future.py
bitmex/ccxt/async_support/base/ws/order_book.py
bitmex/ccxt/async_support/base/ws/order_book_side.py
bitmex/ccxt/base/__init__.py
bitmex/ccxt/base/decimal_to_precision.py
bitmex/ccxt/base/errors.py
bitmex/ccxt/base/exchange.py
bitmex/ccxt/base/precise.py
bitmex/ccxt/base/types.py
bitmex/ccxt/pro/__init__.py
bitmex/ccxt/pro/bitmex.py
bitmex/ccxt/static_dependencies/README.md
bitmex/ccxt/static_dependencies/__init__.py
bitmex/ccxt/static_dependencies/bip/__init__.py
bitmex/ccxt/static_dependencies/bip/addr/P2PKH_addr.py
bitmex/ccxt/static_dependencies/bip/addr/__init__.py
bitmex/ccxt/static_dependencies/bip/addr/addr_dec_utils.py
bitmex/ccxt/static_dependencies/bip/addr/addr_key_validator.py
bitmex/ccxt/static_dependencies/bip/addr/iaddr_decoder.py
bitmex/ccxt/static_dependencies/bip/addr/iaddr_encoder.py
bitmex/ccxt/static_dependencies/bip/base58/__init__.py
bitmex/ccxt/static_dependencies/bip/base58/base58.py
bitmex/ccxt/static_dependencies/bip/base58/base58_ex.py
bitmex/ccxt/static_dependencies/bip/base58/base58_xmr.py
bitmex/ccxt/static_dependencies/bip/bech32/__init__.py
bitmex/ccxt/static_dependencies/bip/bech32/bch_bech32.py
bitmex/ccxt/static_dependencies/bip/bech32/bech32.py
bitmex/ccxt/static_dependencies/bip/bech32/bech32_base.py
bitmex/ccxt/static_dependencies/bip/bech32/bech32_ex.py
bitmex/ccxt/static_dependencies/bip/bech32/segwit_bech32.py
bitmex/ccxt/static_dependencies/bip/bip32/__init__.py
bitmex_api-0.0.120.dist-info/METADATA
bitmex_api-0.0.120.dist-info/WHEEL
bitmex_api-0.0.120.dist-info/RECORD
